bert_multitask_learning/__init__.py
bert_multitask_learning/_nbdev.py
bert_multitask_learning/ckpt_restore_hook.py
bert_multitask_learning/experimental_top.py
bert_multitask_learning/export_model.py
bert_multitask_learning/input_fn.py
bert_multitask_learning/metrics.py
bert_multitask_learning/model_fn.py
bert_multitask_learning/modeling.py
bert_multitask_learning/optimizer.py
bert_multitask_learning/params.py
bert_multitask_learning/preproc_decorator.py
bert_multitask_learning/read_write_tfrecord.py
bert_multitask_learning/run_bert_multitask.py
bert_multitask_learning/special_tokens.py
bert_multitask_learning/test_base.py
bert_multitask_learning/tf_encoder_decoder_generate.py
bert_multitask_learning/top.py
bert_multitask_learning/top_utils.py
bert_multitask_learning/transformers_tf_bart.py
bert_multitask_learning/tutorial.py
bert_multitask_learning/utils.py
bert_multitask_learning/bert_preprocessing/__init__.py
bert_multitask_learning/bert_preprocessing/bert_utils.py
bert_multitask_learning/bert_preprocessing/create_bert_features.py
bert_multitask_learning/predefined_problems/__init__.py
bert_multitask_learning/predefined_problems/cws_data.py
bert_multitask_learning/predefined_problems/ner_data.py
bert_multitask_learning/predefined_problems/test_data.py
tests/__init__.py
tests/script_to_test_run.py
tests/test_base.py
tests/test_input_fn.py
tests/test_read_write_tfrecord.py
tests/test_run_bert_multitask.py
tests/test_utils.py
bert_multitask_learning-0.7.0.dist-info/LICENSE
bert_multitask_learning-0.7.0.dist-info/METADATA
bert_multitask_learning-0.7.0.dist-info/WHEEL
bert_multitask_learning-0.7.0.dist-info/top_level.txt
bert_multitask_learning-0.7.0.dist-info/RECORD
